smoothfit/__about__.py
smoothfit/__init__.py
smoothfit/_license_validation.py
smoothfit/_main.py
smoothfit-0.4.1.dist-info/METADATA
smoothfit-0.4.1.dist-info/WHEEL
smoothfit-0.4.1.dist-info/top_level.txt
smoothfit-0.4.1.dist-info/RECORD
