Metadata-Version: 2.1
Name: smoothfit
Version: 0.4.1
Summary: Smooth data fitting in N dimensions
Author-email: Nico Schlömer <nico.schloemer@gmail.com>
Project-URL: Homepage, https://github.com/sigma-py/smoothfit
Project-URL: Issues, https://github.com/sigma-py/smoothfit/issues
Classifier: Development Status :: 5 - Production/Stable
Classifier: Intended Audience :: Science/Research
Classifier: License :: Other/Proprietary License
Classifier: Operating System :: OS Independent
Classifier: Programming Language :: Python
Classifier: Programming Language :: Python :: 3
Classifier: Programming Language :: Python :: 3.7
Classifier: Programming Language :: Python :: 3.8
Classifier: Programming Language :: Python :: 3.9
Classifier: Programming Language :: Python :: 3.10
Classifier: Programming Language :: Python :: 3.11
Classifier: Topic :: Scientific/Engineering
Classifier: Topic :: Utilities
Requires-Python: >=3.7
Requires-Dist: x21 (>=0.4.10,<0.5.0)
Requires-Dist: krylov
Requires-Dist: numpy
Requires-Dist: scikit-fem[all] (>=3.0.0)
Requires-Dist: scipy
